warmer.py
py_lambda_warmer-0.1.6.dist-info/LICENSE
py_lambda_warmer-0.1.6.dist-info/METADATA
py_lambda_warmer-0.1.6.dist-info/WHEEL
py_lambda_warmer-0.1.6.dist-info/top_level.txt
py_lambda_warmer-0.1.6.dist-info/RECORD
