Metadata-Version: 2.1
Name: py-lambda-warmer
Version: 0.1.6
Summary: Warmer Utility for Lambda Function
Home-page: https://github.com/satyamsoni2211/LambdaWarmerPy.git
Author: satyam soni
Author-email: satyamsoni@hotmail.co.uk
License: mit
Keywords: lambda cold start warming performance
Platform: UNKNOWN
Classifier: Development Status :: 5 - Production/Stable
Classifier: Intended Audience :: Developers
Classifier: Intended Audience :: Information Technology
Classifier: License :: OSI Approved :: MIT License
Classifier: License :: Freeware
Classifier: Operating System :: OS Independent
Classifier: Programming Language :: Python :: 3.6
Classifier: Programming Language :: Python :: 3.7
Classifier: Programming Language :: Python :: 3.8
Classifier: Programming Language :: Python :: 3.9
Classifier: Topic :: Utilities
License-File: LICENSE
Provides-Extra: dev
Requires-Dist: pytest ; extra == 'dev'
Requires-Dist: tox ; extra == 'dev'
